MANIFEST.in
setup.cfg
setup.py
d1_certificate_python/__init__.py
d1_certificate_python/certificate_extractor.py
d1_certificate_python/subject_info.py
dataone.certificate_extensions.egg-info/PKG-INFO
dataone.certificate_extensions.egg-info/SOURCES.txt
dataone.certificate_extensions.egg-info/dependency_links.txt
dataone.certificate_extensions.egg-info/requires.txt
dataone.certificate_extensions.egg-info/top_level.txt
extensions/d1_x509v3_certificate_extractor.c
extensions/d1_x509v3_certificate_generator.c
tests/all_tests.py
tests/test_subject_info.py
tests/test_x509v3_extractor.py
tests/test_x509v3_generator.py
tests/files/accessPolicy1.xml
tests/files/accessPolicy2.xml
tests/files/accessPolicy3.xml
tests/files/certificate.pem
tests/files/pippin.pem
tests/files/subjectInfo1.xml
tests/files/subjectInfo2.xml
tests/files/subjectInfo3.xml
tests/test_files/ca_test.crt
tests/test_files/ca_test.key
tests/test_files/new_cert_private_key.pem
tests/test_files/new_cert_public_key.pem
tests/test_files/subject_info.xml