Metadata-Version: 1.0
Name: dataone.certificate-extensions
Version: 1.1.3
Summary: Python extensions for generating and extracting PEM formatted X.509 v3 certificates that contain DataONE Session information
Home-page: http://dataone.org
Author: DataONE Project
Author-email: developers@dataone.org
License: Apache License, Version 2.0
Platform: UNKNOWN
